LICENSE
README.md
setup.py
bin/silently-commit
silent_committer/__init__.py
silent_committer/silent_committer.xsh
silent_committer/split_diff_to_maximum_hunks.sh
silent_committer.egg-info/PKG-INFO
silent_committer.egg-info/SOURCES.txt
silent_committer.egg-info/dependency_links.txt
silent_committer.egg-info/requires.txt
silent_committer.egg-info/top_level.txt